{
  "last_updated": "2026-01-05 07:11:13",
  "trends": [
    {
      "keyword": "new year's day",
      "score": 57000000,
      "traffic_numeric": 5000000,
      "category": "娱乐/生活",
      "timestamp": "2026-01-04 19:01:32"
    },
    {
      "keyword": "new year's eve",
      "score": 55000000,
      "traffic_numeric": 5000000,
      "category": "娱乐/生活",
      "timestamp": "2026-01-04 13:24:27"
    },
    {
      "keyword": "maduro",
      "score": 25000001,
      "traffic_numeric": 5000000,
      "category": "其他",
      "timestamp": "2026-01-05 07:11:13"
    },
    {
      "keyword": "ole miss vs georgia",
      "score": 18000000,
      "traffic_numeric": 2000000,
      "category": "体育",
      "timestamp": "2026-01-04 03:13:46"
    },
    {
      "keyword": "did eleven die in stranger things",
      "score": 14000000,
      "traffic_numeric": 2000000,
      "category": "其他",
      "timestamp": "2026-01-04 07:10:21"
    },
    {
      "keyword": "alabama vs indiana",
      "score": 12000000,
      "traffic_numeric": 2000000,
      "category": "体育",
      "timestamp": "2026-01-03 13:26:44"
    },
    {
      "keyword": "seahawks vs 49ers",
      "score": 7100000,
      "traffic_numeric": 2000000,
      "category": "体育",
      "timestamp": "2026-01-04 19:01:32"
    },
    {
      "keyword": "brigitte bardot",
      "score": 7000000,
      "traffic_numeric": 1000000,
      "category": "其他",
      "timestamp": "2026-01-03 13:26:44"
    },
    {
      "keyword": "venezuela",
      "score": 6000000,
      "traffic_numeric": 5000000,
      "category": "其他",
      "timestamp": "2026-01-03 18:56:33"
    },
    {
      "keyword": "tatiana schlossberg",
      "score": 5500000,
      "traffic_numeric": 500000,
      "category": "其他",
      "timestamp": "2026-01-04 19:01:32"
    },
    {
      "keyword": "alix earle",
      "score": 4500000,
      "traffic_numeric": 500000,
      "category": "其他",
      "timestamp": "2026-01-04 13:24:27"
    },
    {
      "keyword": "full moon january 2026",
      "score": 4100000,
      "traffic_numeric": 500000,
      "category": "其他",
      "timestamp": "2026-01-05 03:10:32"
    },
    {
      "keyword": "panthers vs buccaneers",
      "score": 4000000,
      "traffic_numeric": 1000000,
      "category": "体育",
      "timestamp": "2026-01-04 19:01:32"
    },
    {
      "keyword": "minnesota fraud",
      "score": 3500000,
      "traffic_numeric": 500000,
      "category": "其他",
      "timestamp": "2026-01-03 13:26:44"
    },
    {
      "keyword": "ravens vs steelers",
      "score": 3000000,
      "traffic_numeric": 2000000,
      "category": "体育",
      "timestamp": "2026-01-05 07:11:13"
    },
    {
      "keyword": "tommy lee jones",
      "score": 3000000,
      "traffic_numeric": 500000,
      "category": "其他",
      "timestamp": "2026-01-05 07:11:13"
    },
    {
      "keyword": "mtv",
      "score": 2800000,
      "traffic_numeric": 200000,
      "category": "其他",
      "timestamp": "2026-01-05 07:11:13"
    },
    {
      "keyword": "curt cignetti",
      "score": 2300000,
      "traffic_numeric": 2000000,
      "category": "其他",
      "timestamp": "2026-01-04 13:24:27"
    },
    {
      "keyword": "anthony joshua car crash",
      "score": 2200000,
      "traffic_numeric": 200000,
      "category": "其他",
      "timestamp": "2026-01-04 13:24:27"
    },
    {
      "keyword": "jodi hildebrandt",
      "score": 2100000,
      "traffic_numeric": 200000,
      "category": "其他",
      "timestamp": "2026-01-05 07:11:13"
    },
    {
      "keyword": "cowboys vs giants",
      "score": 2000000,
      "traffic_numeric": 1000000,
      "category": "体育",
      "timestamp": "2026-01-05 07:11:13"
    },
    {
      "keyword": "nfl playoff schedule",
      "score": 2000000,
      "traffic_numeric": 1000000,
      "category": "体育",
      "timestamp": "2026-01-05 07:11:13"
    },
    {
      "keyword": "lions vs bears",
      "score": 2000000,
      "traffic_numeric": 1000000,
      "category": "体育",
      "timestamp": "2026-01-05 07:11:13"
    },
    {
      "keyword": "commanders vs eagles",
      "score": 2000000,
      "traffic_numeric": 1000000,
      "category": "体育",
      "timestamp": "2026-01-05 07:11:13"
    },
    {
      "keyword": "iran",
      "score": 1600000,
      "traffic_numeric": 200000,
      "category": "其他",
      "timestamp": "2026-01-03 18:56:33"
    },
    {
      "keyword": "winter classic 2026",
      "score": 1600000,
      "traffic_numeric": 200000,
      "category": "其他",
      "timestamp": "2026-01-03 18:56:33"
    },
    {
      "keyword": "camila mendoza olmos",
      "score": 1400000,
      "traffic_numeric": 200000,
      "category": "其他",
      "timestamp": "2026-01-03 13:26:44"
    },
    {
      "keyword": "trevon diggs",
      "score": 1400000,
      "traffic_numeric": 200000,
      "category": "其他",
      "timestamp": "2026-01-03 13:26:44"
    },
    {
      "keyword": "piper rockelle",
      "score": 1300000,
      "traffic_numeric": 200000,
      "category": "其他",
      "timestamp": "2026-01-05 07:11:13"
    },
    {
      "keyword": "packers vs vikings",
      "score": 1200000,
      "traffic_numeric": 500000,
      "category": "体育",
      "timestamp": "2026-01-05 07:11:13"
    }
  ],
  "category_stats": {
    "其他": 40,
    "体育": 32,
    "娱乐/生活": 4,
    "科技/AI": 3
  },
  "insights": [
    {
      "title": "季节性效率/计划应用",
      "context": "新年计划相关关键词搜索量激增。",
      "suggestion": "开发带有社交对赌性质的‘新年目标达成’应用，通过押金模式强制用户坚持习惯。"
    }
  ]
}