{
  "last_updated": "2026-02-21 07:33:48",
  "trends": [
    {
      "keyword": "james van der beek",
      "score": 90000000,
      "traffic_numeric": 5000000,
      "category": "其他",
      "timestamp": "2026-02-18 13:56:49"
    },
    {
      "keyword": "2026 winter olympics men figure skating",
      "score": 50000000,
      "traffic_numeric": 5000000,
      "category": "其他",
      "timestamp": "2026-02-16 13:56:55"
    },
    {
      "keyword": "robert duvall",
      "score": 36500000,
      "traffic_numeric": 2000000,
      "category": "其他",
      "timestamp": "2026-02-21 07:33:48"
    },
    {
      "keyword": "2026 winter olympics women single skating free skating",
      "score": 33000000,
      "traffic_numeric": 5000000,
      "category": "其他",
      "timestamp": "2026-02-21 07:33:48"
    },
    {
      "keyword": "elana meyers taylor",
      "score": 30000000,
      "traffic_numeric": 5000000,
      "category": "其他",
      "timestamp": "2026-02-18 07:44:49"
    },
    {
      "keyword": "eric dane",
      "score": 21000000,
      "traffic_numeric": 5000000,
      "category": "其他",
      "timestamp": "2026-02-21 07:33:48"
    },
    {
      "keyword": "2026 winter olympics alpine skiing",
      "score": 18700000,
      "traffic_numeric": 2000000,
      "category": "其他",
      "timestamp": "2026-02-17 19:48:30"
    },
    {
      "keyword": "jesse jackson",
      "score": 15200000,
      "traffic_numeric": 1000000,
      "category": "其他",
      "timestamp": "2026-02-21 07:33:48"
    },
    {
      "keyword": "pam bondi",
      "score": 15000000,
      "traffic_numeric": 1000000,
      "category": "其他",
      "timestamp": "2026-02-18 03:41:38"
    },
    {
      "keyword": "wuthering heights movie",
      "score": 14200000,
      "traffic_numeric": 2000000,
      "category": "娱乐/生活",
      "timestamp": "2026-02-17 19:48:30"
    },
    {
      "keyword": "mikaela shiffrin",
      "score": 10000000,
      "traffic_numeric": 5000000,
      "category": "其他",
      "timestamp": "2026-02-19 07:52:15"
    },
    {
      "keyword": "lunar new year",
      "score": 9000000,
      "traffic_numeric": 2000000,
      "category": "娱乐/生活",
      "timestamp": "2026-02-18 19:45:21"
    },
    {
      "keyword": "lil poppa",
      "score": 8000000,
      "traffic_numeric": 1000000,
      "category": "其他",
      "timestamp": "2026-02-21 07:33:48"
    },
    {
      "keyword": "michael jordan",
      "score": 7200000,
      "traffic_numeric": 1000000,
      "category": "其他",
      "timestamp": "2026-02-21 03:24:16"
    },
    {
      "keyword": "2026 winter olympics men's snowboarding slopestyle",
      "score": 6720000,
      "traffic_numeric": 5000000,
      "category": "其他",
      "timestamp": "2026-02-19 14:09:34"
    },
    {
      "keyword": "prince andrew",
      "score": 6700000,
      "traffic_numeric": 1000000,
      "category": "其他",
      "timestamp": "2026-02-21 07:33:48"
    },
    {
      "keyword": "shia labeouf",
      "score": 6200000,
      "traffic_numeric": 500000,
      "category": "其他",
      "timestamp": "2026-02-21 07:33:48"
    },
    {
      "keyword": "ricky martin",
      "score": 6000000,
      "traffic_numeric": 2000000,
      "category": "其他",
      "timestamp": "2026-02-15 19:15:14"
    },
    {
      "keyword": "ash wednesday",
      "score": 5500000,
      "traffic_numeric": 1000000,
      "category": "其他",
      "timestamp": "2026-02-20 03:31:39"
    },
    {
      "keyword": "usa hockey",
      "score": 5000000,
      "traffic_numeric": 1000000,
      "category": "其他",
      "timestamp": "2026-02-17 13:54:43"
    },
    {
      "keyword": "alysa liu",
      "score": 4500000,
      "traffic_numeric": 2000000,
      "category": "其他",
      "timestamp": "2026-02-21 07:33:48"
    },
    {
      "keyword": "ramadan 2026",
      "score": 3800000,
      "traffic_numeric": 500000,
      "category": "其他",
      "timestamp": "2026-02-19 14:09:34"
    },
    {
      "keyword": "olympic hockey",
      "score": 3800000,
      "traffic_numeric": 1000000,
      "category": "其他",
      "timestamp": "2026-02-17 13:54:43"
    },
    {
      "keyword": "rhode island shooting",
      "score": 3600000,
      "traffic_numeric": 500000,
      "category": "其他",
      "timestamp": "2026-02-19 03:32:49"
    },
    {
      "keyword": "jessica alba",
      "score": 3500000,
      "traffic_numeric": 500000,
      "category": "其他",
      "timestamp": "2026-02-15 19:15:14"
    },
    {
      "keyword": "daytona 500",
      "score": 3400000,
      "traffic_numeric": 1000000,
      "category": "其他",
      "timestamp": "2026-02-16 19:23:58"
    },
    {
      "keyword": "james talarico",
      "score": 3170000,
      "traffic_numeric": 500000,
      "category": "其他",
      "timestamp": "2026-02-21 07:33:48"
    },
    {
      "keyword": "is youtube down",
      "score": 3000000,
      "traffic_numeric": 1000000,
      "category": "其他",
      "timestamp": "2026-02-18 13:56:49"
    },
    {
      "keyword": "youtube down",
      "score": 3000000,
      "traffic_numeric": 1000000,
      "category": "其他",
      "timestamp": "2026-02-19 07:52:15"
    },
    {
      "keyword": "carolyn bessette kennedy",
      "score": 2700000,
      "traffic_numeric": 500000,
      "category": "其他",
      "timestamp": "2026-02-19 07:52:15"
    }
  ],
  "category_stats": {
    "其他": 139,
    "体育": 27,
    "娱乐/生活": 11,
    "科技/AI": 8,
    "金融/商业": 1
  },
  "insights": [
    {
      "title": "季节性效率/计划应用",
      "context": "新年计划相关关键词搜索量激增。",
      "suggestion": "开发带有社交对赌性质的‘新年目标达成’应用，通过押金模式强制用户坚持习惯。"
    }
  ]
}