{
  "last_updated": "2026-05-19 10:38:43",
  "trends": [
    {
      "keyword": "brandon clarke",
      "score": 25500000,
      "traffic_numeric": 1000000,
      "category": "其他",
      "timestamp": "2026-05-19 10:38:43"
    },
    {
      "keyword": "pistons vs cavaliers",
      "score": 19500000,
      "traffic_numeric": 2000000,
      "category": "体育",
      "timestamp": "2026-05-16 14:19:34"
    },
    {
      "keyword": "drake",
      "score": 13900000,
      "traffic_numeric": 1000000,
      "category": "其他",
      "timestamp": "2026-05-19 10:38:43"
    },
    {
      "keyword": "gina carano",
      "score": 10700000,
      "traffic_numeric": 2000000,
      "category": "其他",
      "timestamp": "2026-05-18 10:59:47"
    },
    {
      "keyword": "chelsea handler",
      "score": 9600000,
      "traffic_numeric": 500000,
      "category": "其他",
      "timestamp": "2026-05-17 19:53:04"
    },
    {
      "keyword": "pga championship",
      "score": 8500000,
      "traffic_numeric": 1000000,
      "category": "其他",
      "timestamp": "2026-05-17 08:54:57"
    },
    {
      "keyword": "tony hinchcliffe",
      "score": 8300000,
      "traffic_numeric": 500000,
      "category": "其他",
      "timestamp": "2026-05-17 19:53:04"
    },
    {
      "keyword": "sheryl underwood",
      "score": 7800000,
      "traffic_numeric": 500000,
      "category": "其他",
      "timestamp": "2026-05-17 19:53:04"
    },
    {
      "keyword": "swatch",
      "score": 7000000,
      "traffic_numeric": 2000000,
      "category": "其他",
      "timestamp": "2026-05-13 20:33:39"
    },
    {
      "keyword": "alex murdaugh",
      "score": 6950000,
      "traffic_numeric": 500000,
      "category": "其他",
      "timestamp": "2026-05-19 10:38:43"
    },
    {
      "keyword": "jason collins",
      "score": 6700000,
      "traffic_numeric": 500000,
      "category": "其他",
      "timestamp": "2026-05-18 04:58:20"
    },
    {
      "keyword": "off campus",
      "score": 6650000,
      "traffic_numeric": 500000,
      "category": "其他",
      "timestamp": "2026-05-18 20:27:57"
    },
    {
      "keyword": "hantavirus map",
      "score": 6200000,
      "traffic_numeric": 1000000,
      "category": "其他",
      "timestamp": "2026-05-14 15:16:00"
    },
    {
      "keyword": "ap swatch collab",
      "score": 5000000,
      "traffic_numeric": 1000000,
      "category": "其他",
      "timestamp": "2026-05-15 04:48:53"
    },
    {
      "keyword": "air force monica witt",
      "score": 4700000,
      "traffic_numeric": 500000,
      "category": "科技/AI",
      "timestamp": "2026-05-19 10:38:43"
    },
    {
      "keyword": "aaron rai",
      "score": 4500000,
      "traffic_numeric": 1000000,
      "category": "科技/AI",
      "timestamp": "2026-05-19 10:38:43"
    },
    {
      "keyword": "spurs vs thunder",
      "score": 4000000,
      "traffic_numeric": 2000000,
      "category": "体育",
      "timestamp": "2026-05-19 10:38:43"
    },
    {
      "keyword": "thunder vs lakers",
      "score": 4000000,
      "traffic_numeric": 2000000,
      "category": "体育",
      "timestamp": "2026-05-12 20:25:54"
    },
    {
      "keyword": "regina hall",
      "score": 3600000,
      "traffic_numeric": 200000,
      "category": "其他",
      "timestamp": "2026-05-17 19:53:04"
    },
    {
      "keyword": "nba draft",
      "score": 3000000,
      "traffic_numeric": 1000000,
      "category": "体育",
      "timestamp": "2026-05-13 15:51:52"
    },
    {
      "keyword": "swatch ap",
      "score": 3000000,
      "traffic_numeric": 1000000,
      "category": "其他",
      "timestamp": "2026-05-15 20:10:55"
    },
    {
      "keyword": "nate diaz",
      "score": 2900000,
      "traffic_numeric": 500000,
      "category": "其他",
      "timestamp": "2026-05-18 20:27:57"
    },
    {
      "keyword": "mackenzie shirilla",
      "score": 2900000,
      "traffic_numeric": 500000,
      "category": "其他",
      "timestamp": "2026-05-19 10:38:43"
    },
    {
      "keyword": "obsession",
      "score": 2800000,
      "traffic_numeric": 500000,
      "category": "其他",
      "timestamp": "2026-05-19 10:38:43"
    },
    {
      "keyword": "remarkably bright creatures",
      "score": 2700000,
      "traffic_numeric": 500000,
      "category": "其他",
      "timestamp": "2026-05-13 20:33:39"
    },
    {
      "keyword": "ap watch",
      "score": 2500000,
      "traffic_numeric": 1000000,
      "category": "其他",
      "timestamp": "2026-05-16 14:19:34"
    },
    {
      "keyword": "pga championship 2026",
      "score": 2400000,
      "traffic_numeric": 500000,
      "category": "其他",
      "timestamp": "2026-05-16 19:49:29"
    },
    {
      "keyword": "nfl schedule",
      "score": 2400000,
      "traffic_numeric": 500000,
      "category": "体育",
      "timestamp": "2026-05-15 20:10:55"
    },
    {
      "keyword": "giants vs dodgers",
      "score": 2200000,
      "traffic_numeric": 500000,
      "category": "体育",
      "timestamp": "2026-05-15 20:10:55"
    },
    {
      "keyword": "tigers vs mets",
      "score": 2050000,
      "traffic_numeric": 1000000,
      "category": "体育",
      "timestamp": "2026-05-14 20:20:54"
    }
  ],
  "category_stats": {
    "其他": 91,
    "体育": 34,
    "科技/AI": 6,
    "娱乐/生活": 4,
    "金融/商业": 2
  },
  "insights": []
}