{
  "last_updated": "2026-06-13 05:20:00",
  "trends": [
    {
      "keyword": "james handy",
      "score": 40000000,
      "traffic_numeric": 2000000,
      "category": "其他",
      "timestamp": "2026-06-11 16:45:38"
    },
    {
      "keyword": "knicks vs spurs game 3",
      "score": 30900000,
      "traffic_numeric": 5000000,
      "category": "体育",
      "timestamp": "2026-06-11 11:21:44"
    },
    {
      "keyword": "knicks vs spurs game 5",
      "score": 25000000,
      "traffic_numeric": 5000000,
      "category": "体育",
      "timestamp": "2026-06-13 05:20:00"
    },
    {
      "keyword": "la mayor race",
      "score": 22000000,
      "traffic_numeric": 2000000,
      "category": "其他",
      "timestamp": "2026-06-08 21:18:43"
    },
    {
      "keyword": "fifa world cup 2026",
      "score": 21400002,
      "traffic_numeric": 5000000,
      "category": "其他",
      "timestamp": "2026-06-13 05:20:00"
    },
    {
      "keyword": "knicks vs spurs game 4",
      "score": 20000000,
      "traffic_numeric": 5000000,
      "category": "体育",
      "timestamp": "2026-06-11 21:08:44"
    },
    {
      "keyword": "california election results",
      "score": 17500000,
      "traffic_numeric": 2000000,
      "category": "其他",
      "timestamp": "2026-06-09 15:55:59"
    },
    {
      "keyword": "world cup",
      "score": 15500000,
      "traffic_numeric": 5000000,
      "category": "其他",
      "timestamp": "2026-06-12 16:08:25"
    },
    {
      "keyword": "karmelo anthony",
      "score": 15000000,
      "traffic_numeric": 2000000,
      "category": "其他",
      "timestamp": "2026-06-11 16:45:38"
    },
    {
      "keyword": "spurs vs knicks game 3",
      "score": 10500000,
      "traffic_numeric": 5000000,
      "category": "体育",
      "timestamp": "2026-06-10 05:16:13"
    },
    {
      "keyword": "austin metcalf",
      "score": 8200000,
      "traffic_numeric": 2000000,
      "category": "其他",
      "timestamp": "2026-06-13 05:20:00"
    },
    {
      "keyword": "california governor race",
      "score": 8000000,
      "traffic_numeric": 2000000,
      "category": "其他",
      "timestamp": "2026-06-08 21:18:43"
    },
    {
      "keyword": "masters of the universe",
      "score": 7700000,
      "traffic_numeric": 2000000,
      "category": "其他",
      "timestamp": "2026-06-09 04:52:17"
    },
    {
      "keyword": "mexico vs south africa",
      "score": 6650000,
      "traffic_numeric": 2000000,
      "category": "体育",
      "timestamp": "2026-06-13 05:20:00"
    },
    {
      "keyword": "anthony head",
      "score": 5700000,
      "traffic_numeric": 500000,
      "category": "其他",
      "timestamp": "2026-06-09 04:52:17"
    },
    {
      "keyword": "spurs vs knicks",
      "score": 5500001,
      "traffic_numeric": 5000000,
      "category": "体育",
      "timestamp": "2026-06-11 11:21:44"
    },
    {
      "keyword": "spacex stock",
      "score": 5400000,
      "traffic_numeric": 2000000,
      "category": "金融/商业",
      "timestamp": "2026-06-13 05:20:00"
    },
    {
      "keyword": "82-0 game",
      "score": 5100000,
      "traffic_numeric": 500000,
      "category": "娱乐/生活",
      "timestamp": "2026-06-09 20:36:59"
    },
    {
      "keyword": "og anunoby",
      "score": 5000000,
      "traffic_numeric": 5000000,
      "category": "其他",
      "timestamp": "2026-06-11 16:45:38"
    },
    {
      "keyword": "world cup schedule",
      "score": 4700000,
      "traffic_numeric": 2000000,
      "category": "其他",
      "timestamp": "2026-06-12 16:08:25"
    },
    {
      "keyword": "bitcoin price",
      "score": 4400000,
      "traffic_numeric": 500000,
      "category": "金融/商业",
      "timestamp": "2026-06-08 16:51:21"
    },
    {
      "keyword": "game 3 nba finals",
      "score": 4200000,
      "traffic_numeric": 2000000,
      "category": "体育",
      "timestamp": "2026-06-09 15:55:59"
    },
    {
      "keyword": "heat advisory",
      "score": 3950000,
      "traffic_numeric": 500000,
      "category": "其他",
      "timestamp": "2026-06-13 05:20:00"
    },
    {
      "keyword": "usa vs germany",
      "score": 3700000,
      "traffic_numeric": 1000000,
      "category": "体育",
      "timestamp": "2026-06-08 05:27:21"
    },
    {
      "keyword": "god of war laufey",
      "score": 3600000,
      "traffic_numeric": 500000,
      "category": "其他",
      "timestamp": "2026-06-09 04:52:17"
    },
    {
      "keyword": "south korea vs czechia",
      "score": 3050000,
      "traffic_numeric": 1000000,
      "category": "体育",
      "timestamp": "2026-06-13 05:20:00"
    },
    {
      "keyword": "simone biles",
      "score": 3000000,
      "traffic_numeric": 200000,
      "category": "其他",
      "timestamp": "2026-06-13 05:20:00"
    },
    {
      "keyword": "myles garrett",
      "score": 2700000,
      "traffic_numeric": 500000,
      "category": "其他",
      "timestamp": "2026-06-07 20:11:46"
    },
    {
      "keyword": "carmelo anthony",
      "score": 2220000,
      "traffic_numeric": 2000000,
      "category": "其他",
      "timestamp": "2026-06-11 21:08:44"
    },
    {
      "keyword": "fifa world cup 2026™",
      "score": 2220000,
      "traffic_numeric": 1000000,
      "category": "其他",
      "timestamp": "2026-06-13 05:20:00"
    }
  ],
  "category_stats": {
    "其他": 113,
    "体育": 47,
    "娱乐/生活": 13,
    "科技/AI": 10,
    "金融/商业": 3
  },
  "insights": [
    {
      "title": "季节性效率/计划应用",
      "context": "新年计划相关关键词搜索量激增。",
      "suggestion": "开发带有社交对赌性质的‘新年目标达成’应用，通过押金模式强制用户坚持习惯。"
    }
  ]
}